ngitung/BangunDatar.py
ngitung/__init__.py
ngitung-0.1.0.dist-info/METADATA
ngitung-0.1.0.dist-info/WHEEL
ngitung-0.1.0.dist-info/top_level.txt
ngitung-0.1.0.dist-info/RECORD
