Metadata-Version: 2.1
Name: ngitung
Version: 0.1.0
Summary: Uji Coba Library Python Sederhana
Home-page: UNKNOWN
Author: Mahasin
Author-email: mmasadar@gmail.com
License: MIT
Platform: UNKNOWN
